Workbook

Sheet Assumptions
A1: Assumption | B1: Value
A2: Revenue Growth Rate | B2: 0.05
A3: Operating Margin | B3: 0.2
A4: Tax Rate | B4: 0.25
A5: Interest Rate | B5: 0.05
A6: Capex (% of Rev) | B6: 0.08

Sheet Income Statement
A1: Line Item | B1: 2023 (Prior) | C1: 2024 (Current)
A2: Revenue | B2: 1000 | C2: =B2*(1+Assumptions!B2)
A3: Operating Expenses | B3: 800 | C3: =C2*(1-Assumptions!B3)
A4: EBITDA | B4: =B2-B3 | C4: =C2-C3
A5: Depreciation | B5: 50 | C5: 50
A6: EBIT | B6: =B4-B5 | C6: =C4-C5
A7: Interest Expense | B7: 10 | C7: ='Balance Sheet'!C7*Assumptions!B5
A8: EBT | B8: =B6-B7 | C8: =C6-C7
A9: Tax Expense | B9: =B8*Assumptions!B4 | C9: =C8*Assumptions!B4
A10: Net Income | B10: =B8-B9 | C10: =C8-C9

Sheet Balance Sheet
A1: Line Item | B1: 2023 (Prior) | C1: 2024 (Current)
A2: Cash | B2: 300 | C2: ='Cash Flow Statement'!B12
A3: Accounts Receivable | B3: 100 | C3: 100
A4: Property, Plant & Equipment (Net) | B4: 500 | C4: =B4-'Cash Flow Statement'!B6-'Income Statement'!C5
A5: Total Assets | B5: =SUM(B2:B4) | C5: =SUM(C2:C4)
A6: Accounts Payable | B6: 100 | C6: 100
A7: Long-Term Debt | B7: 200 | C7: 200
A8: Total Liabilities | B8: =SUM(B6:B7) | C8: =SUM(C6:C7)
A9: Common Stock | B9: 300 | C9: 300
A10: Retained Earnings | B10: 300 | C10: =B10+'Income Statement'!C10
A11: Total Equity | B11: =SUM(B9:B10) | C11: =SUM(C9:C10)
A12: Total Liabilities & Equity | B12: =B8+B11 | C12: =C8+C11

Sheet Cash Flow Statement
A1: Line Item | B1: 2024 (Current)
A2: Net Income | B2: ='Income Statement'!C10
A3: Depreciation & Amortization | B3: ='Income Statement'!C5
A4: Change in Working Capital | B4: 0
A5: Cash Flow from Operations | B5: =SUM(B2:B4)
A6: Capital Expenditures | B6: =-'Income Statement'!C2*Assumptions!B6
A7: Cash Flow from Investing | B7: =B6
A8: Debt Repayment / Issuance | B8: 0
A9: Cash Flow from Financing | B9: =B8
A10: Net Change in Cash | B10: =B5+B7+B9
A11: Beginning Cash | B11: ='Balance Sheet'!B2
A12: Ending Cash | B12: =B11+B10
